demo_libry_lokesh/__init__.py
demo_libry_lokesh/demo_functions.py
demolibrary-0.1.2.dist-info/licenses/LICENSE
demolibrary-0.1.2.dist-info/METADATA
demolibrary-0.1.2.dist-info/WHEEL
demolibrary-0.1.2.dist-info/top_level.txt
demolibrary-0.1.2.dist-info/RECORD
