Metadata-Version: 2.4
Name: demolibrary
Version: 0.1.2
Summary: Add your description here
Requires-Python: >=3.12
License-File: LICENSE
Requires-Dist: numpy>=2.4.0
Requires-Dist: pandas>=2.3.3
Requires-Dist: pytest>=9.0.2
Dynamic: license-file
